Outliers/Outliers.py
Outliers/__init__.py
Outliers_Arsh-0.0.1.dist-info/LICENSE.txt
Outliers_Arsh-0.0.1.dist-info/METADATA
Outliers_Arsh-0.0.1.dist-info/WHEEL
Outliers_Arsh-0.0.1.dist-info/top_level.txt
Outliers_Arsh-0.0.1.dist-info/RECORD
