Metadata-Version: 2.1
Name: Outliers-Arsh
Version: 0.0.1
Summary: Outliers package
Home-page: UNKNOWN
Author: ARSHPREET SINGH
Author-email: arshpreet15.99@gmail.com
License: UNKNOWN
Platform: UNKNOWN
Classifier: Programming Language :: Python :: 3
Classifier: License :: OSI Approved :: MIT License
Classifier: Operating System :: OS Independent
Requires-Python: >=3.6
